AUTHORS
LICENSE
MANIFEST.in
README.rst
setup.py
django_pytds/__init__.py
django_pytds/base.py
django_pytds/compiler.py
django_pytds/creation.py
django_pytds/fields.py
django_pytds/introspection.py
django_pytds/operations.py
django_pytds/patches.py
django_pytds/south_adapter.py
django_pytds/timezone.py
django_pytds.egg-info/PKG-INFO
django_pytds.egg-info/SOURCES.txt
django_pytds.egg-info/dependency_links.txt
django_pytds.egg-info/requires.txt
django_pytds.egg-info/top_level.txt
django_pytds.egg-info/zip-safe
django_pytds/models/__init__.py
django_pytds/models/manager.py
django_pytds/models/query.py
django_pytds/sql_app/__init__.py
django_pytds/sql_app/management/__init__.py
django_pytds/sql_app/management/commands/__init__.py
django_pytds/sql_app/management/commands/dbgui.py