Metadata-Version: 1.0
Name: django-pytds
Version: 0.3
Summary: Django backend database support for MS SQL 2005 and up.
Home-page: https://bitbucket.org/denisenkom/django-pytds
Author: Mikhail Denisenko
Author-email: denisenkom@gmail.com
License: MIT
Platform: UNKNOWN
Classifier: Development Status :: 4 - Beta
Classifier: Framework :: Django
Classifier: Programming Language :: Python
Classifier: Programming Language :: Python :: 2.7
Classifier: Topic :: Internet :: WWW/HTTP
